Metadata-Version: 2.1
Name: substr
Version: 0.0.1
Summary: Python package for working with substrings.
Home-page: https://github.com/CodeConfidant/substr
Author: Drew Hainer
Author-email: codeconfidant@gmail.com
License: MIT
Platform: Windows
Platform: Linux
License-File: LICENSE
